DataStructures/AbstractDataStructures.py
DataStructures/Errors.py
DataStructures/TreeDataStructures.py
DataStructures/__init__.py
pythonic_data_structures-0.1.dist-info/METADATA
pythonic_data_structures-0.1.dist-info/RECORD
pythonic_data_structures-0.1.dist-info/WHEEL
pythonic_data_structures-0.1.dist-info/top_level.txt
