Metadata-Version: 2.1
Name: pythonic-data-structures
Version: 0.1
Summary: Python-based implementations for many data structures.
Home-page: https://github.com/nikist97/Python-DataStructures
Author: Nikolay Stanchev
Author-email: nikist97.ns@gmail.com
License: Apache 2.0
Keywords: data structures,data,structures,python,abstract,generic,graph,heap,queue,stack
Platform: UNKNOWN
Classifier: License :: OSI Approved :: Apache Software License
Classifier: Programming Language :: Python :: 3
Classifier: Topic :: Software Development :: Libraries :: Python Modules
Requires-Python: >=3
